README.md
setup.cfg
setup.py
pymixconf/__init__.py
pymixconf/jsonconf.py
pymixconf/mixconf.py
pymixconf/yamlconf.py
pymixconf.egg-info/PKG-INFO
pymixconf.egg-info/SOURCES.txt
pymixconf.egg-info/dependency_links.txt
pymixconf.egg-info/requires.txt
pymixconf.egg-info/top_level.txt